{
    "data": {
        "merchant": "Quick 73",
        "date": "Jun 26, 15",
        "menu": [
            {
                "Artikel": "1 Beef Ribs",
                "Total": "36.86"
            },
            {
                "Artikel": "1 Pulled Pork Sand",
                "Total": "8.50"
            },
            {
                "Artikel": "1 Creamed Corn[Small]",
                "Total": "3.35"
            },
            {
                "Artikel": "1 Longhorn Mac & Cheese[sm]",
                "Total": "4.20"
            },
            {
                "Artikel": "1 Chocolate Cake[Slice]",
                "Total": "3.95"
            },
            {
                "Artikel": "1 Fountain Soda",
                "Total": "2.25"
            }
        ],
        "total": "64.43"
    }
}