{
    "data": {
        "merchant": "Nonna",
        "date": "2012-05-21",
        "menu": [
            {
                "Artikel": "Tartare di Tonno",
                "Total": "17.00"
            },
            {
                "Artikel": "Linguine Scampi",
                "Total": "20.00"
            },
            {
                "Artikel": "Branzino",
                "Total": "28.00"
            },
            {
                "Artikel": "Pizza Americana",
                "Total": "14.00"
            },
            {
                "Artikel": "Carrot Cake",
                "Total": "12.00"
            },
            {
                "Artikel": "Gl Sangiovese",
                "Total": "12.00"
            },
            {
                "Artikel": "Gl Merlot",
                "Total": "13.00"
            },
            {
                "Artikel": "Misc Food",
                "Total": "2.00"
            }
        ],
        "total": "128.33"
    }
}